huobitrade/EmailInform.py
huobitrade/__init__.py
huobitrade/core.py
huobitrade/datatype.py
huobitrade/handler.py
huobitrade/main.py
huobitrade/service.py
huobitrade/utils.py
huobitrade/extra/loggging_handler.py
huobitrade/extra/rpc.py
huobitrade-0.5.6.dist-info/METADATA
huobitrade-0.5.6.dist-info/RECORD
huobitrade-0.5.6.dist-info/WHEEL
huobitrade-0.5.6.dist-info/entry_points.txt
huobitrade-0.5.6.dist-info/top_level.txt
