Metadata-Version: 2.1
Name: huobitrade
Version: 0.5.6
Summary: HuoBi Trading Framwork(python)
Home-page: https://hadrianl.github.io/huobi/
Author: Hadrianl
Author-email: 137150224@qq.com
License: UNKNOWN
Platform: UNKNOWN
Classifier: Development Status :: 5 - Production/Stable
Classifier: Natural Language :: Chinese (Simplified)
Classifier: Operating System :: MacOS
Classifier: Operating System :: Microsoft :: Windows
Classifier: Operating System :: POSIX :: Linux
Classifier: Programming Language :: Python :: Implementation :: CPython
Classifier: Programming Language :: Python :: 3.6
Classifier: Programming Language :: Python :: 3.7
Classifier: License :: OSI Approved :: MIT License
Classifier: Topic :: Software Development :: Libraries :: Python Modules
Classifier: Topic :: Software Development :: Version Control :: Git
Requires-Dist: websocket-client (>=0.53)
Requires-Dist: requests
Requires-Dist: pymongo
Requires-Dist: pyzmq
Requires-Dist: pandas
Requires-Dist: requests-futures
Requires-Dist: ecdsa
Requires-Dist: click
